eyetea/__init__.py
eyetea/__main__.py
eyetea/events.py
eyetea/server/__init__.py
eyetea/server/downloads.py
eyetea/server/pastables.py
eyetea/server/shells/__init__.py
eyetea/server/shells/reverse.py
eyetea/server/shells/utilities.py
eyetea/server/templates/shells/reverse/linux_bash.jinja
eyetea/server/templates/shells/reverse/linux_host.jinja
eyetea/server/templates/shells/reverse/linux_host_auto.jinja
eyetea/server/templates/shells/reverse/linux_python3.jinja
eyetea/server/templates/shells/reverse/linux_target.jinja
eyetea/server/templates/shells/reverse/windows_powershell.jinja
eyetea/server/templates/shells/reverse/windows_python3.jinja
eyetea/server/templates/shells/reverse/windows_target.jinja
eyetea/server/templates/shells/utilities/linux_bash.jinja
eyetea/server/templates/shells/utilities/linux_target.jinja
eyetea/server/templates/shells/utilities/windows_powershell.jinja
eyetea/server/templates/shells/utilities/windows_target.jinja
eyetea/server/uploads.py
eyetea/ui/__init__.py
eyetea/ui/static/eyetea.tcss
eyetea/ui/widgets.py
eyetea/utilities.py
eyetea-0.1.1.dist-info/LICENSE
eyetea-0.1.1.dist-info/METADATA
eyetea-0.1.1.dist-info/WHEEL
eyetea-0.1.1.dist-info/entry_points.txt
eyetea-0.1.1.dist-info/RECORD
